perfect_freehand/__init__.py
perfect_freehand/py.typed
perfect_freehand/types.py
perfect_freehand/vec.py
perfect_freehand-1.2.0.dist-info/CC0-1.0.txt
perfect_freehand-1.2.0.dist-info/METADATA
perfect_freehand-1.2.0.dist-info/MIT.txt
perfect_freehand-1.2.0.dist-info/WHEEL
perfect_freehand-1.2.0.dist-info/top_level.txt
perfect_freehand-1.2.0.dist-info/RECORD
