Metadata-Version: 2.1
Name: perfect-freehand
Version: 1.2.0
Summary: Draw perfect pressure-sensitive freehand lines. (Python port)
Home-page: https://docs.bigbluebutton.org/perfect-freehand-python/
Author: Calvin Walton
Maintainer: Calvin Walton
Maintainer-email: calvin.walton@kepstin.ca
Project-URL: Bug Tracker, https://github.com/bigbluebutton/perfect-freehand-python/issues
Classifier: Development Status :: 3 - Alpha
Classifier: Intended Audience :: Developers
Classifier: Programming Language :: Python :: 3
Classifier: License :: OSI Approved :: MIT License
Classifier: Operating System :: OS Independent
Classifier: Topic :: Multimedia :: Graphics :: Editors :: Vector-Based
License-File: LICENSES/CC0-1.0.txt
License-File: LICENSES/MIT.txt
